django_sse4htmx/__init__.py
django_sse4htmx/py.typed
django_sse4htmx/sender.py
django_sse4htmx-0.1.1.dist-info/METADATA
django_sse4htmx-0.1.1.dist-info/WHEEL
django_sse4htmx-0.1.1.dist-info/RECORD
