Metadata-Version: 2.4
Name: django-sse4htmx
Version: 0.1.1
Summary: A simple wrapper around Django EventStream's `send_event` to make it simpler to use with HTMX and django-template-partials.
Project-URL: Repository, https://github.com/eyesee1/django-sse4htmx
Project-URL: Documentation, https://github.com/eyesee1/django-sse4htmx
Project-URL: Issues, https://github.com/eyesee1/django-sse4htmx/issues
Author-email: "Duna C." <marinas.bobble-05@icloud.com>
Maintainer-email: "Duna C." <marinas.bobble-05@icloud.com>
Classifier: Development Status :: 4 - Beta
Classifier: Framework :: Django
Classifier: Intended Audience :: Developers
Classifier: License :: OSI Approved :: MIT License
Classifier: Topic :: Internet :: WWW/HTTP :: Dynamic Content
Classifier: Topic :: Text Processing :: Markup :: HTML
Requires-Python: >=3.11.6
Requires-Dist: django-eventstream>=5.3.1
Requires-Dist: django>=5.0
